[
  {
    "name": "Даниил Сергеев",
    "nickname": "sergeev.d",
    "roles": [
      { "name": "студент", "colorMain": "--xi-green-100", "colorSecondary": "--xi-green-0" },
      { "name": "1", "colorMain": "--xi-gray-80", "colorSecondary": "--xi-gray-5" }
    ],
    "isOwner": false
  },
  {
    "name": "Ксения Любина",
    "nickname": "lybina",
    "roles": [
      { "name": "студент", "colorMain": "--xi-green-100", "colorSecondary": "--xi-green-0" }
    ],
    "isOwner": false
  },
  {
    "name": "Денис Спиридонов",
    "nickname": "dspiridonov",
    "roles": [
      { "name": "студент", "colorMain": "--xi-green-100", "colorSecondary": "--xi-green-0" }
    ],
    "isOwner": false
  },
  {
    "name": "Анна Иванова",
    "nickname": "lybina",
    "roles": [
      { "name": "преподаватель", "colorMain": "--xi-brand-100", "colorSecondary": "--xi-brand-0" },
      {
        "name": "администратор",
        "colorMain": "--xi-violet-100",
        "colorSecondary": "--xi-violet-20"
      }
    ],
    "isOwner": true
  },
  {
    "name": "Иван Ковыляев",
    "nickname": "ikovylyaev",
    "roles": [
      {
        "name": "администратор",
        "colorMain": "--xi-violet-100",
        "colorSecondary": "--xi-violet-20"
      },
      { "name": "студент", "colorMain": "--xi-green-100", "colorSecondary": "--xi-green-0" },
      {
        "name": "администратор",
        "colorMain": "--xi-violet-100",
        "colorSecondary": "--xi-violet-20"
      },
      {
        "name": "администратор",
        "colorMain": "--xi-violet-100",
        "colorSecondary": "--xi-violet-20"
      },
      {
        "name": "администратор",
        "colorMain": "--xi-violet-100",
        "colorSecondary": "--xi-violet-20"
      }
    ],
    "isOwner": false
  }
]
